svg3d/__init__.py
svg3d/shaders.py
svg3d/svg3d.py
svg3d/utils.py
svg3d/view.py
svg3d-0.2.1.dist-info/licenses/LICENSE
svg3d-0.2.1.dist-info/METADATA
svg3d-0.2.1.dist-info/WHEEL
svg3d-0.2.1.dist-info/top_level.txt
svg3d-0.2.1.dist-info/RECORD
