Metadata-Version: 2.4
Name: svg3d
Version: 0.2.1
Summary: Minimal library for rendering polyhedra as SVG wireframes.
Author-email: Jen Bradley <jenbrad@umich.edu>
License: MIT License
Project-URL: Source, https://github.com/janbridley/svg3d
Project-URL: Issues, https://github.com/janbridley/svg3d/issues
Requires-Python: >=3.11
License-File: LICENSE
Requires-Dist: numpy>=1.19.1
Requires-Dist: svgwrite
Requires-Dist: tqdm
Provides-Extra: tests
Requires-Dist: coxeter; extra == "tests"
Requires-Dist: hypothesis; extra == "tests"
Requires-Dist: pyrr; extra == "tests"
Requires-Dist: pytest; extra == "tests"
Requires-Dist: rowan; extra == "tests"
Dynamic: license-file
